XCCPyPDF/__init__.py
XCCPyPDF/_version.py
XCCPyPDF/filters.py
XCCPyPDF/generic.py
XCCPyPDF/merger.py
XCCPyPDF/pagerange.py
XCCPyPDF/pdf.py
XCCPyPDF/utils.py
XCCPyPDF/xmp.py
XCCPyPDF-1.26.0.dist-info/LICENSE
XCCPyPDF-1.26.0.dist-info/METADATA
XCCPyPDF-1.26.0.dist-info/WHEEL
XCCPyPDF-1.26.0.dist-info/top_level.txt
XCCPyPDF-1.26.0.dist-info/RECORD
