Metadata-Version: 2.1
Name: XCCPyPDF
Version: 1.26.0
Summary: PDF toolkit
Home-page: UNKNOWN
Author: white.tie
Author-email: 
Maintainer: Phaseit, Inc.
Maintainer-email: 
License: UNKNOWN
Platform: UNKNOWN
Classifier: Development Status :: 5 - Production/Stable
Classifier: Intended Audience :: Developers
Classifier: License :: OSI Approved :: BSD License
Classifier: Programming Language :: Python :: 2
Classifier: Programming Language :: Python :: 3
Classifier: Operating System :: OS Independent
Classifier: Topic :: Software Development :: Libraries :: Python Modules
